MANIFEST.in
README.rst
setup.py
iabjad/__init__.py
iabjad/iabjad.py
iabjad.egg-info/PKG-INFO
iabjad.egg-info/SOURCES.txt
iabjad.egg-info/dependency_links.txt
iabjad.egg-info/not-zip-safe
iabjad.egg-info/requires.txt
iabjad.egg-info/top_level.txt