Metadata-Version: 1.0
Name: iabjad
Version: 0.2
Summary: Utilities to work with Abjad from IPython
Home-page: https://github.com/cryptonomicon314/iabjad.git
Author: Cryptonomicon
Author-email: cryptonomicon.314@gmail.com
License: MIT
Platform: UNKNOWN
